bcdc_apitests/__init__.py
bcdc_apitests/conftest.py
bcdc_apitests/pytest-run.py
bcdc_apitests/pytest.ini
bcdc_apitests/config/__init__.py
bcdc_apitests/config/testConfig.py
bcdc_apitests/fixtures/__init__.py
bcdc_apitests/fixtures/arguements.py
bcdc_apitests/fixtures/cached_data.py
bcdc_apitests/fixtures/ckan.py
bcdc_apitests/fixtures/config_fixture.py
bcdc_apitests/fixtures/dynamic_data.py
bcdc_apitests/fixtures/groups.py
bcdc_apitests/fixtures/load_config.py
bcdc_apitests/fixtures/load_data.py
bcdc_apitests/fixtures/orgs.py
bcdc_apitests/fixtures/packages.py
bcdc_apitests/fixtures/resources.py
bcdc_apitests/fixtures/scheming.py
bcdc_apitests/fixtures/setup_fixtures.py
bcdc_apitests/fixtures/users.py
bcdc_apitests/helpers/__init__.py
bcdc_apitests/helpers/bcdc_dataset_schema.py
bcdc_apitests/helpers/bcdc_dynamic_data_population.py
bcdc_apitests/helpers/file_utils.py
bcdc_apitests/helpers/read_test_config.py
bcdc_apitests/helpers/read_user_config.py
bcdc_apitests/helpers/test_bcdc_dynamic_data_population.py
bcdc_apitests/test_data/ckan_core_schema.json
bcdc_apitests/test_data/ckan_core_schema.readme.md
bcdc_apitests/test_data/data_schema.json
bcdc_apitests/test_data/group.json
bcdc_apitests/test_data/ownerOrg.json
bcdc_apitests/test_data/pkgData.json
bcdc_apitests/test_data/pkgDataData-1.json
bcdc_apitests/test_data/pkgDataGeo-1.json
bcdc_apitests/test_data/pkgData_min.json
bcdc_apitests/test_data/resource.json
bcdc_apitests/test_data/testParams.json
bcdc_apitests/test_data/testParams_old.json
bcdc_apitests/tests/__init__.py
bcdc_apitests/tests/groups/__init__.py
bcdc_apitests/tests/groups/conftest.py
bcdc_apitests/tests/groups/test_groups.py
bcdc_apitests/tests/organizations/__init__.py
bcdc_apitests/tests/organizations/conftest.py
bcdc_apitests/tests/organizations/test_orgs.py
bcdc_apitests/tests/other/__init__.py
bcdc_apitests/tests/other/conftest.py
bcdc_apitests/tests/other/test_other.py
bcdc_apitests/tests/packages/__init__.py
bcdc_apitests_dev-1.0.81.dist-info/LICENSE
bcdc_apitests_dev-1.0.81.dist-info/METADATA
bcdc_apitests_dev-1.0.81.dist-info/WHEEL
bcdc_apitests_dev-1.0.81.dist-info/top_level.txt
bcdc_apitests_dev-1.0.81.dist-info/RECORD
