Metadata-Version: 2.1
Name: bcdc-apitests-dev
Version: 1.0.81
Summary: API testing for BC Data Catalog
Home-page: https://github.com/bcgov/bcdc-test
Author: Kevin Netherton
Author-email: kevin.netherton@gov.bc.ca
License: UNKNOWN
Platform: UNKNOWN
Classifier: Development Status :: 4 - Beta
Classifier: Framework :: Pytest
Classifier: Programming Language :: Python :: 2.7
Classifier: License :: OSI Approved :: Apache Software License
Classifier: Topic :: Software Development :: Testing
Classifier: Operating System :: OS Independent
Requires-Python: >=2.6, !=3.0.*, !=3.1.*, !=3.2.*, <4
Requires-Dist: pypandoc (==1.4)
Requires-Dist: ckanapi (==4.3)
Requires-Dist: pytest (==4.6.2)
Requires-Dist: requests (==2.22.0)
Requires-Dist: pytest-check (==0.3.5)
Requires-Dist: distlib (==0.2.9)
Requires-Dist: pytest-json (==0.4.0)
Requires-Dist: randomwordgenerator (==1.0.0)
